haystack_human_tool-0.2.0.dist-info/METADATA
haystack_human_tool-0.2.0.dist-info/WHEEL
haystack_human_tool-0.2.0.dist-info/licenses/LICENSE
haystack_human_tool/__init__.py
haystack_human_tool/humaninloop.py
haystack_human_tool/prompt_templates.py
haystack_human_tool-0.2.0.dist-info/RECORD
