Metadata-Version: 2.1
Name: haystack-human-tool
Version: 0.2.0
Summary: A human in the loop tool to refine queries. For use with haystack agents
Author-Email: Roland Tannous <rolandtannous@gravityml.com>
License: MIT
Classifier: Programming Language :: Python :: 3
Classifier: License :: OSI Approved :: MIT License
Classifier: Operating System :: OS Independent
Project-URL: Homepage, https://github.com/gravityml/haystack-human-tool
Project-URL: Bug tracker, https://github.com/gravityml/haystack-human-tool/issues
Requires-Python: >=3.9.16
Requires-Dist: farm-haystack>=1.15.0
Requires-Dist: redis
Requires-Dist: haystack-memory
Requires-Dist: bleach
